snapgene_reader/__init__.py
snapgene_reader/snapgene_reader.py
snapgene_reader/version.py
snapgene_reader-0.1.23.dist-info/licenses/LICENSE
snapgene_reader-0.1.23.dist-info/METADATA
snapgene_reader-0.1.23.dist-info/WHEEL
snapgene_reader-0.1.23.dist-info/top_level.txt
snapgene_reader-0.1.23.dist-info/RECORD
