Metadata-Version: 2.4
Name: snapgene_reader
Version: 0.1.23
Summary: Convert Snapgene *.dna files dict/json/biopython.
Author: yishaluo
License-Expression: MIT
Project-URL: Homepage, https://github.com/Edinburgh-Genome-Foundry/SnapGeneReader
Keywords: DNA,sequence,design,format,converter
License-File: LICENSE
Requires-Dist: biopython
Requires-Dist: xmltodict
Requires-Dist: html2text
Dynamic: license-file
